Melchizedek/__init__.py
Melchizedek/test_module.py
Melchizedek-0.0.4.dist-info/LICENCE.txt
Melchizedek-0.0.4.dist-info/METADATA
Melchizedek-0.0.4.dist-info/WHEEL
Melchizedek-0.0.4.dist-info/top_level.txt
Melchizedek-0.0.4.dist-info/RECORD
